codepass/__init__.py
codepass/__main__.py
codepass/file_report.py
codepass/get_config.py
codepass/get_report_file.py
codepass/llm/a_score_parser.py
codepass/llm/b_score_parser.py
codepass/llm/estimate_a_score_prompt.py
codepass/llm/estimate_b_score_prompt.py
codepass/llm/improvement_suggestion_parser.py
codepass/llm/improvement_suggestion_prompt.py
codepass/llm/model.py
codepass/main.py
codepass/parallel_runtime.py
codepass/read_code_files.py
codepass/scores/evaluate_a_score.py
codepass/scores/evaluate_b_score.py
codepass/scores/suggest_improvements.py
codepass/token_budget_estimator.py
codepass/utils.py
codepass-0.3.5.dist-info/LICENSE.txt
codepass-0.3.5.dist-info/METADATA
codepass-0.3.5.dist-info/WHEEL
codepass-0.3.5.dist-info/entry_points.txt
codepass-0.3.5.dist-info/RECORD
