Metadata-Version: 2.1
Name: codepass
Version: 0.3.5
Summary: A CLI tool to evaluate the quality of your code
Author: airtucha
Author-email: airtucha@gmail.com
Requires-Python: >=3.9,<4.0
Classifier: Programming Language :: Python :: 3
Classifier: Programming Language :: Python :: 3.9
Classifier: Programming Language :: Python :: 3.10
Classifier: Programming Language :: Python :: 3.11
Classifier: Programming Language :: Python :: 3.12
Requires-Dist: colorama (>=0.4.6,<0.5.0)
Requires-Dist: langchain (>=0.3.2,<0.4.0)
Requires-Dist: langchain-community (>=0.3.1,<0.4.0)
Requires-Dist: langchain-core (>=0.3.10,<0.4.0)
Requires-Dist: langchain-openai (>=0.2.2,<0.3.0)
Requires-Dist: mypy (==1.9.0)
Requires-Dist: typer (>=0.12.5,<0.13.0)
